api_rule_engine/__init__.py
api_rule_engine/client.py
api_rule_engine-0.0.21.data/scripts/api-rule-engine
api_rule_engine-0.0.21.dist-info/LICENSE
api_rule_engine-0.0.21.dist-info/METADATA
api_rule_engine-0.0.21.dist-info/WHEEL
api_rule_engine-0.0.21.dist-info/top_level.txt
api_rule_engine-0.0.21.dist-info/RECORD
