Metadata-Version: 2.1
Name: api-rule-engine
Version: 0.0.21
Summary: rule engine API
Home-page: https://github.com/somerl20/api-rule-engine.git
Author: Omer London
License: GNU
Platform: UNKNOWN
License-File: LICENSE
Requires-Dist: requests (>=2.25.1)
